ocpp_broker/__init__.py
ocpp_broker/api_server.py
ocpp_broker/backend_manager.py
ocpp_broker/broker.py
ocpp_broker/charge_point.py
ocpp_broker/config.py
ocpp_broker/data_transfer_handler.py
ocpp_broker/middleware.py
ocpp_broker/ocpp_command_api.py
ocpp_broker/registry.py
ocpp_broker/server.py
ocpp_broker/session.py
ocpp_broker/tag_api.py
ocpp_broker/tag_manager.py
ocpp_broker/schemas/__init__.py
ocpp_broker/schemas/tags.py
ocpp_broker-0.3.dist-info/METADATA
ocpp_broker-0.3.dist-info/WHEEL
ocpp_broker-0.3.dist-info/entry_points.txt
ocpp_broker-0.3.dist-info/top_level.txt
ocpp_broker-0.3.dist-info/RECORD
