Metadata-Version: 2.4
Name: ocpp-broker
Version: 0.3
Summary: A comprehensive OCPP broker with tag management, message routing, and backend integration
Author-email: Abhas Dudeja <amdudeja@gmail.com>
Requires-Python: >=3.10
Requires-Dist: websockets>=11.0
Requires-Dist: pyyaml>=6.0
Requires-Dist: fastapi>=0.110.0
Requires-Dist: uvicorn>=0.29.0
Requires-Dist: ocpp>=0.13.0
Provides-Extra: tests
Requires-Dist: pytest>=8.0.0; extra == "tests"
Requires-Dist: pytest-asyncio>=0.23.0; extra == "tests"
Requires-Dist: httpx>=0.25.0; extra == "tests"
